{"chunk_definitions":[{"row":9,"row_count":1,"visible":true,"expansion_state":0,"options":{"engine":"r","label":"set","include":false},"document_id":"F3F30B7B","chunk_id":"cxlpt0hwdkr5u","chunk_label":"set"},{"row":103,"row_count":1,"visible":true,"expansion_state":0,"options":{"engine":"r","label":"unnamed-chunk-39"},"document_id":"F3F30B7B","chunk_id":"cil5bqnsuou2y","chunk_label":"unnamed-chunk-2"},{"row":116,"row_count":1,"visible":true,"expansion_state":0,"options":{"engine":"r","label":"unnamed-chunk-40"},"document_id":"F3F30B7B","chunk_id":"cqsh3iua84qc7","chunk_label":"unnamed-chunk-3"},{"row":144,"row_count":1,"visible":true,"expansion_state":0,"options":{"engine":"r","label":"unnamed-chunk-42"},"document_id":"F3F30B7B","chunk_id":"cf0n3f6hf2nzr","chunk_label":"unnamed-chunk-7"}],"doc_write_time":1652131644}